navicat_volcanic/__init__.py
navicat_volcanic/__main__.py
navicat_volcanic/dv1.py
navicat_volcanic/dv2.py
navicat_volcanic/exceptions.py
navicat_volcanic/helpers.py
navicat_volcanic/plotting2d.py
navicat_volcanic/plotting3d.py
navicat_volcanic/test_modules.py
navicat_volcanic/tof.py
navicat_volcanic/volcanic.py
navicat_volcanic-1.3.3.dist-info/LICENSE
navicat_volcanic-1.3.3.dist-info/METADATA
navicat_volcanic-1.3.3.dist-info/WHEEL
navicat_volcanic-1.3.3.dist-info/entry_points.txt
navicat_volcanic-1.3.3.dist-info/top_level.txt
navicat_volcanic-1.3.3.dist-info/RECORD
