Metadata-Version: 2.1
Name: navicat-volcanic
Version: 1.3.3
Summary: Modular Analysis of Representative Conformers
Home-page: https://github.com/lcmd-epfl/volcanic/
Author: rlaplaza, lcmd-epfl
Author-email: "R. Laplaza" <rlaplaza@duck.com>
Keywords: compchem
Classifier: Programming Language :: Python :: 3
Classifier: License :: OSI Approved :: MIT License
Classifier: Operating System :: OS Independent
Requires-Python: >=3.8
License-File: LICENSE
Requires-Dist: h5py >=3.3.0
Requires-Dist: matplotlib >=3.6.1
Requires-Dist: numpy >=1.23.4
Requires-Dist: pandas >=1.5.0
Requires-Dist: scikit-learn >=1.2.0
Requires-Dist: scipy >=1.9.1
Requires-Dist: setuptools >=65.4.1
